django_inline_static-0.1.0.dist-info/METADATA
django_inline_static-0.1.0.dist-info/RECORD
django_inline_static-0.1.0.dist-info/WHEEL
django_inline_static-0.1.0.dist-info/top_level.txt
inline_static/__init__.py
inline_static/css.py
inline_static/loader.py
inline_static/templatetags/__init__.py
inline_static/templatetags/inline_static_tags.py
