Metadata-Version: 2.1
Name: django-inline-static
Version: 0.1.0
Summary: django-inline-static provides template tags to inline css and javascript files in Django templates.
Home-page: https://github.com/moccu/django-inline-static
Author: Moccu GmbH & Co. KG
Author-email: info@moccu.com
License: UNKNOWN
Project-URL: Bug Reports, https://github.com/moccu/django-inline-static/issues
Project-URL: Source, https://github.com/moccu/django-inline-static
Keywords: django static templates
Platform: UNKNOWN
Classifier: Development Status :: 4 - Beta
Classifier: Environment :: Web Environment
Classifier: Framework :: Django
Classifier: Intended Audience :: Developers
Classifier: License :: OSI Approved :: MIT License
Classifier: Programming Language :: Python :: 3
Classifier: Programming Language :: Python :: 3.6
